chinillabip158.cpython-37m-aarch64-linux-gnu.so
chinillabip158-1.2.1.dist-info/top_level.txt
chinillabip158-1.2.1.dist-info/WHEEL
chinillabip158-1.2.1.dist-info/RECORD
chinillabip158-1.2.1.dist-info/LICENSE
chinillabip158-1.2.1.dist-info/METADATA
