Metadata-Version: 2.1
Name: chinillabip158
Version: 1.2.1
Summary: Chinilla BIP158 (wraps C++)
Home-page: https://github.com/Chinilla/chinillabip158
Author: Edward Teach
Author-email: edward@chinilla.com
License: Apache License
Requires-Python: >=3.7
License-File: LICENSE
